bemval/__init__.py
bemval/validator.py
bemval-0.0.7.dist-info/METADATA
bemval-0.0.7.dist-info/WHEEL
bemval-0.0.7.dist-info/top_level.txt
bemval-0.0.7.dist-info/RECORD
