Metadata-Version: 2.1
Name: bemval
Version: 0.0.7
Summary: Super simple and/or basic email validator without using external libraries (i.e. just python std functions)
Home-page: https://github.com/jahirfiquitiva/bemval
Author: Sebastian Mayorga, Jahir Fiquitiva
Author-email: sebastian@soundwave.vip, hi@jahir.xyz
License: MIT
Platform: UNKNOWN
Classifier: License :: OSI Approved :: MIT License
Classifier: Programming Language :: Python :: 3
Classifier: Programming Language :: Python :: 3.6
